odoo/addons/partner_invoicing_mode_at_shipping/README.rst
odoo/addons/partner_invoicing_mode_at_shipping/__init__.py
odoo/addons/partner_invoicing_mode_at_shipping/__manifest__.py
odoo/addons/partner_invoicing_mode_at_shipping/hooks.py
odoo/addons/partner_invoicing_mode_at_shipping/data/queue_job_data.xml
odoo/addons/partner_invoicing_mode_at_shipping/i18n/es.po
odoo/addons/partner_invoicing_mode_at_shipping/i18n/fr.po
odoo/addons/partner_invoicing_mode_at_shipping/i18n/it.po
odoo/addons/partner_invoicing_mode_at_shipping/i18n/partner_invoicing_mode_at_shipping.pot
odoo/addons/partner_invoicing_mode_at_shipping/migrations/16.0.1.1.0/pre-migrate.py
odoo/addons/partner_invoicing_mode_at_shipping/models/__init__.py
odoo/addons/partner_invoicing_mode_at_shipping/models/res_partner.py
odoo/addons/partner_invoicing_mode_at_shipping/models/sale_order.py
odoo/addons/partner_invoicing_mode_at_shipping/models/stock_picking.py
odoo/addons/partner_invoicing_mode_at_shipping/readme/CONTRIBUTORS.md
odoo/addons/partner_invoicing_mode_at_shipping/readme/CREDITS.md
odoo/addons/partner_invoicing_mode_at_shipping/readme/DESCRIPTION.md
odoo/addons/partner_invoicing_mode_at_shipping/static/description/icon.png
odoo/addons/partner_invoicing_mode_at_shipping/static/description/index.html
odoo/addons/partner_invoicing_mode_at_shipping/tests/__init__.py
odoo/addons/partner_invoicing_mode_at_shipping/tests/common.py
odoo/addons/partner_invoicing_mode_at_shipping/tests/test_invoice_mode_at_shipping.py
odoo/addons/partner_invoicing_mode_at_shipping/tests/test_invoice_mode_group_delivery.py
odoo/addons/partner_invoicing_mode_at_shipping/views/res_partner.xml
odoo_addon_partner_invoicing_mode_at_shipping-18.0.1.0.1.dist-info/METADATA
odoo_addon_partner_invoicing_mode_at_shipping-18.0.1.0.1.dist-info/WHEEL
odoo_addon_partner_invoicing_mode_at_shipping-18.0.1.0.1.dist-info/top_level.txt
odoo_addon_partner_invoicing_mode_at_shipping-18.0.1.0.1.dist-info/RECORD
